simplegraphs/__init__.py
simplegraphs/graphs.py
simplegraphs-0.3.0.dist-info/DESCRIPTION.rst
simplegraphs-0.3.0.dist-info/METADATA
simplegraphs-0.3.0.dist-info/RECORD
simplegraphs-0.3.0.dist-info/WHEEL
simplegraphs-0.3.0.dist-info/metadata.json
simplegraphs-0.3.0.dist-info/top_level.txt
