Metadata-Version: 2.0
Name: simplegraphs
Version: 0.3.0
Summary: A python library providing tools for building and analyzing graphs
Home-page: https://github.com/DamourYouKnow/simplegraphs
Author: DamourYouKnow
Author-email: damourba@gmail.com
License: MIT
Platform: UNKNOWN
